app_sdk_zxw/__init__.py
app_sdk_zxw/Errors/__init__.py
app_sdk_zxw/Errors/api_errors.py
app_sdk_zxw/SDK_jwt/__init__.py
app_sdk_zxw/SDK_jwt/demo.py
app_sdk_zxw/SDK_jwt/jwt.py
app_sdk_zxw/SDK_jwt/jwt_刷新管理.py
app_sdk_zxw/SDK_jwt/apis/__init__.py
app_sdk_zxw/SDK_jwt/apis/api_刷新token.py
app_sdk_zxw/SDK_jwt/db_model/__init__.py
app_sdk_zxw/SDK_jwt/db_model/model.py
app_sdk_zxw/SDK_微信/__init__.py
app_sdk_zxw/SDK_微信/SDK_微信公众号或网站应用/__init__.py
app_sdk_zxw/SDK_微信/SDK_微信公众号或网站应用/获取_openid和access_token.py
app_sdk_zxw/SDK_微信/SDK_微信公众号或网站应用/获取_登录二维码URL.py
app_sdk_zxw/SDK_微信/SDK_微信公众号或网站应用/apis/__init__.py
app_sdk_zxw/SDK_微信/SDK_微信公众号或网站应用/apis/api_用户信息.py
app_sdk_zxw/SDK_微信/SDK_微信公众号或网站应用/apis/api_登录二维码.py
app_sdk_zxw/SDK_微信/SDK_微信小程序/__init__.py
app_sdk_zxw/SDK_微信/SDK_微信小程序/step1_维护小程序准入码.py
app_sdk_zxw/SDK_微信/SDK_微信小程序/获取_openid和sessionKey.py
app_sdk_zxw/SDK_微信/SDK_微信小程序/获取小程序二维码.py
app_sdk_zxw/SDK_微信/SDK_微信小程序/解密_用户信息.py
app_sdk_zxw/SDK_微信/SDK_微信小程序/apis/__init__.py
app_sdk_zxw/SDK_微信/SDK_微信小程序/apis/api_用户信息.py
app_sdk_zxw/SDK_微信/SDK_微信小程序/发送订阅消息/__init__.py
app_sdk_zxw/SDK_微信/SDK_微信小程序/发送订阅消息/发送订阅消息.py
app_sdk_zxw/SDK_微信/SDK_微信小程序/发送订阅消息/模板_发货提醒.py
app_sdk_zxw/SDK_微信/SDK_微信支付/__init__.py
app_sdk_zxw/SDK_微信/SDK_微信支付/demo.py
app_sdk_zxw/SDK_微信/SDK_微信支付/微信支付SDK二次打包_可直接调用.py
app_sdk_zxw/SDK_微信/SDK_微信支付/返回值模型.py
app_sdk_zxw/SDK_微信/SDK_微信支付/minipay/__init__.py
app_sdk_zxw/SDK_微信/SDK_微信支付/minipay/base.py
app_sdk_zxw/SDK_微信/SDK_微信支付/minipay/config.py
app_sdk_zxw/SDK_微信/SDK_微信支付/minipay/exceptions.py
app_sdk_zxw/SDK_微信/SDK_微信支付/minipay/model.py
app_sdk_zxw/SDK_微信/apis/__init__.py
app_sdk_zxw/SDK_微信/apis/api_服务器配置验证.py
app_sdk_zxw/SDK_极光推送/__init__.py
app_sdk_zxw/SDK_极光推送/mian.py
app_sdk_zxw/SDK_硬件读写/__init__.py
app_sdk_zxw/SDK_硬件读写/crc16.py
app_sdk_zxw/SDK_硬件读写/异或校验.py
app_sdk_zxw/SDK_硬件读写/根据始末标志位提取数据.py
app_sdk_zxw/SDK_硬件读写/语音播报.py
app_sdk_zxw/SDK_硬件读写/进制转换.py
app_sdk_zxw/SDK_硬件读写/LED显示屏/__init__.py
app_sdk_zxw/SDK_硬件读写/LED显示屏/仰邦BX6K1_RS232.py
app_sdk_zxw-1.0.0.dist-info/METADATA
app_sdk_zxw-1.0.0.dist-info/WHEEL
app_sdk_zxw-1.0.0.dist-info/top_level.txt
app_sdk_zxw-1.0.0.dist-info/RECORD
