Metadata-Version: 2.1
Name: app-sdk-zxw
Version: 1.0.0
Summary: 薛伟的小工具。
Home-page: https://github.com/sunshineinwater/
Author: xue wei zhang
Author-email: 
Classifier: Programming Language :: Python :: 3.9
Classifier: License :: OSI Approved :: MIT License
Classifier: Operating System :: OS Independent
Requires-Dist: httpx ==0.27.0
Requires-Dist: fastapi ==0.112.1
Requires-Dist: sqlalchemy
Requires-Dist: jose
